agentrs-0.1.0.dist-info/METADATA
agentrs-0.1.0.dist-info/WHEEL
agentrs-0.1.0.dist-info/license_files/LICENSE
agentrs/__init__.py
agentrs/agentrs.cpython-311-darwin.so
agentrs-0.1.0.dist-info/RECORD
