Metadata-Version: 2.1
Name: agentrs
Version: 0.1.0
Classifier: Programming Language :: Rust
Classifier: Programming Language :: Python :: Implementation :: CPython
License-File: LICENSE
Summary: Quickly develop and run ABMs! Written in Rust for use in Python.
Author-email: Benedikt Arnarsson <benediktjens.arnarsson@gmail.com>
License: MIT
Requires-Python: >=3.7
